winzy_days_from/__init__.py
winzy_days_from-0.0.1.dist-info/licenses/LICENSE
winzy_days_from-0.0.1.dist-info/METADATA
winzy_days_from-0.0.1.dist-info/WHEEL
winzy_days_from-0.0.1.dist-info/entry_points.txt
winzy_days_from-0.0.1.dist-info/top_level.txt
winzy_days_from-0.0.1.dist-info/RECORD
