Metadata-Version: 2.4
Name: winzy-days-from
Version: 0.0.1
Summary: Calculates future date from number of days
Author: Sukhbinder Singh
License: Apache-2.0
Project-URL: Homepage, https://github.com/sukhbinder/winzy-days-from
Project-URL: Changelog, https://github.com/sukhbinder/winzy-days-from/releases
Project-URL: Issues, https://github.com/sukhbinder/winzy-days-from/issues
Project-URL: CI, https://github.com/sukhbinder/winzy-days-from/actions
Classifier: License :: OSI Approved :: Apache Software License
License-File: LICENSE
Requires-Dist: winzy
Provides-Extra: test
Requires-Dist: pytest; extra == "test"
Dynamic: license-file
